shmkt.py
modules/__init__.py
modules/views.py
shellmarkets-0.0.3.dist-info/METADATA
shellmarkets-0.0.3.dist-info/WHEEL
shellmarkets-0.0.3.dist-info/entry_points.txt
shellmarkets-0.0.3.dist-info/top_level.txt
shellmarkets-0.0.3.dist-info/RECORD
