Metadata-Version: 2.1
Name: shellmarkets
Version: 0.0.3
Summary: A CLI tool for retrieving stock market information.
Home-page: https://github.com/croketillo/SHELLMARKETS
Author: Croketillo
Author-email: croketillo@gmail.com
Classifier: Development Status :: 3 - Alpha
Classifier: Intended Audience :: End Users/Desktop
Classifier: Intended Audience :: Financial and Insurance Industry
Classifier: Natural Language :: English
Classifier: Programming Language :: Python :: 3
Classifier: Programming Language :: Python :: 3.6
Classifier: Programming Language :: Python :: 3.7
Classifier: Programming Language :: Python :: 3.8
Classifier: Programming Language :: Python :: 3.9
Classifier: Programming Language :: Python :: 3.10
Classifier: Programming Language :: Python :: 3.11
Classifier: Topic :: Office/Business :: Financial :: Investment
Classifier: Topic :: Utilities
Requires-Python: >=3.6
Requires-Dist: click
Requires-Dist: yfinance
Requires-Dist: colorama
